{
	"configurations" : 
	[
		{
			"directories" : 
			[
				{
					"build" : ".",
					"jsonFile" : "directory-.-Debug-f5ebdc15457944623624.json",
					"minimumCMakeVersion" : 
					{
						"string" : "3.21"
					},
					"projectIndex" : 0,
					"source" : ".",
					"targetIndexes" : 
					[
						0
					]
				}
			],
			"name" : "Debug",
			"projects" : 
			[
				{
					"directoryIndexes" : 
					[
						0
					],
					"name" : "CppKillerApp",
					"targetIndexes" : 
					[
						0
					]
				}
			],
			"targets" : 
			[
				{
					"directoryIndex" : 0,
					"id" : "CppKillerApp::@6890427a1f51a3e7e1df",
					"jsonFile" : "target-CppKillerApp-Debug-4fcfacb7cd5e7206765e.json",
					"name" : "CppKillerApp",
					"projectIndex" : 0
				}
			]
		}
	],
	"kind" : "codemodel",
	"paths" : 
	{
		"build" : "/home/felix/Workspaces/playground/Cpp/CppKillerApp/cmake-build-debug",
		"source" : "/home/felix/Workspaces/playground/Cpp/CppKillerApp"
	},
	"version" : 
	{
		"major" : 2,
		"minor" : 3
	}
}
